bochscpu/_bochscpu.cpython-311-aarch64-linux-gnu.so
bochscpu/__init__.py
bochscpu/_bochscpu/__init__.pyi
bochscpu/_bochscpu/cpu/__init__.pyi
bochscpu/_bochscpu/memory/__init__.pyi
bochscpu/cpu/__init__.py
bochscpu/utils/callbacks.py
bochscpu/utils/cpu.py
bochscpu/utils/__init__.py
bochscpu/memory/__init__.py
bochscpu_python-0.4.0.dist-info/METADATA
bochscpu_python-0.4.0.dist-info/RECORD
bochscpu_python-0.4.0.dist-info/WHEEL
bochscpu_python-0.4.0.dist-info/licenses/LICENSE
