Metadata-Version: 2.1
Name: bochscpu-python
Version: 0.4.0
Summary: Python bindings for BochsCPU.
Author-Email: hugsy <hugsy@blah.cat>
License: MIT License
Classifier: Development Status :: 4 - Beta
Classifier: License :: OSI Approved :: MIT License
Classifier: Programming Language :: Python :: 3
Classifier: Programming Language :: Python :: 3.9
Classifier: Programming Language :: Python :: 3.10
Classifier: Programming Language :: Python :: 3.11
Classifier: Programming Language :: Python :: 3.12
Classifier: Programming Language :: Python :: 3.13
Classifier: Topic :: System :: Emulators
Classifier: Natural Language :: English
Project-URL: Homepage, https://github.com/hugsy/bochscpu-python
Requires-Python: >=3.9
Requires-Dist: setuptools
Requires-Dist: wheel
Requires-Dist: nanobind
Requires-Dist: pytest; extra == "tests"
Requires-Dist: black; extra == "tests"
Requires-Dist: capstone; extra == "tests"
Requires-Dist: keystone-engine; extra == "tests"
Provides-Extra: tests
